openfoodfacts/__init__.py
openfoodfacts/api.py
openfoodfacts/barcode.py
openfoodfacts/dataset.py
openfoodfacts/images.py
openfoodfacts/ingredients.py
openfoodfacts/ml/image_classification.py
openfoodfacts/ml/object_detection.py
openfoodfacts/ml/triton.py
openfoodfacts/ml/utils.py
openfoodfacts/ocr.py
openfoodfacts/py.typed
openfoodfacts/redis.py
openfoodfacts/taxonomy.py
openfoodfacts/types.py
openfoodfacts/utils/__init__.py
openfoodfacts/utils/fold_to_ascii.py
openfoodfacts/utils/text.py
openfoodfacts-3.0.0.dist-info/LICENSE
openfoodfacts-3.0.0.dist-info/LICENSES/CC0-1.0.txt
openfoodfacts-3.0.0.dist-info/LICENSES/MIT.txt
openfoodfacts-3.0.0.dist-info/METADATA
openfoodfacts-3.0.0.dist-info/WHEEL
openfoodfacts-3.0.0.dist-info/RECORD
