Metadata-Version: 2.3
Name: openfoodfacts
Version: 3.0.0
Summary: Official Python SDK of Open Food Facts
License: MIT
Author: The Open Food Facts team
Author-email: contact@openfoodfacts.org
Requires-Python: >=3.10
Classifier: Development Status :: 5 - Production/Stable
Classifier: Intended Audience :: Developers
Classifier: License :: OSI Approved :: MIT License
Classifier: Natural Language :: English
Classifier: Programming Language :: Python :: 3
Classifier: Programming Language :: Python :: 3.10
Classifier: Programming Language :: Python :: 3.11
Classifier: Programming Language :: Python :: 3.12
Classifier: Programming Language :: Python :: 3.13
Classifier: Programming Language :: Python :: Implementation :: CPython
Classifier: Programming Language :: Python :: Implementation :: PyPy
Provides-Extra: ml
Provides-Extra: pillow
Provides-Extra: redis
Requires-Dist: Pillow ; extra == "ml"
Requires-Dist: Pillow ; extra == "pillow"
Requires-Dist: opencv-python-headless ; extra == "ml"
Requires-Dist: pydantic (>=2.0.0,<3.0.0)
Requires-Dist: redis ; extra == "redis"
Requires-Dist: requests (>=2.20.0)
Requires-Dist: tqdm (>=4.0.0,<5.0.0)
Requires-Dist: tritonclient[grpc] ; extra == "ml"
Project-URL: Repository, https://github.com/openfoodfacts/openfoodfacts-python
